jsonm/__init__.py
jsonm/application.py
jsonm/fields.py
jsonm/model.py
jsonm/vals.py
jsonm/contrib/__init__.py
jsonm/contrib/datetime_models.py
jsonm-1.1.2.dist-info/METADATA
jsonm-1.1.2.dist-info/WHEEL
jsonm-1.1.2.dist-info/top_level.txt
jsonm-1.1.2.dist-info/RECORD
