Metadata-Version: 2.1
Name: jsonm
Version: 1.1.2
Summary: python object to or from json
Home-page: https://github.com/dantezhu/jsonm
Author: dantezhu
Author-email: dantezhu <dantezhu@qq.com>
License: MIT
Project-URL: Homepage, https://github.com/dantezhu/jsonm
